phanes/__init__.py
phanes/common.py
phanes/phanes.py
phanes-0.0.2.dist-info/LICENSE
phanes-0.0.2.dist-info/METADATA
phanes-0.0.2.dist-info/WHEEL
phanes-0.0.2.dist-info/entry_points.txt
phanes-0.0.2.dist-info/top_level.txt
phanes-0.0.2.dist-info/RECORD
