Metadata-Version: 2.2
Name: phanes
Version: 0.0.2
Summary: Python Package
Author-email: John Riedl <john.riedl@icloud.com>
License: MIT License
Project-URL: Homepage, https://github.com/jriedl1/phanes
Keywords: phanes
Classifier: Intended Audience :: Developers
Classifier: License :: OSI Approved :: MIT License
Classifier: Natural Language :: English
Classifier: Programming Language :: Python :: 3.8
Classifier: Programming Language :: Python :: 3.9
Classifier: Programming Language :: Python :: 3.10
Classifier: Programming Language :: Python :: 3.11
Classifier: Programming Language :: Python :: 3.12
Requires-Python: >=3.8
License-File: LICENSE
Requires-Dist: numpy
Provides-Extra: all
Requires-Dist: phanes[extra]; extra == "all"
Provides-Extra: extra
Requires-Dist: pandas; extra == "extra"
